thumbor_hsl/__init__.py
thumbor_hsl/loaders/__init__.py
thumbor_hsl/loaders/http_loader.py
thumbor_hsl-0.0.3.dist-info/LICENSE
thumbor_hsl-0.0.3.dist-info/METADATA
thumbor_hsl-0.0.3.dist-info/WHEEL
thumbor_hsl-0.0.3.dist-info/top_level.txt
thumbor_hsl-0.0.3.dist-info/RECORD
