Metadata-Version: 2.1
Name: thumbor-hsl
Version: 0.0.3
Summary: A modified `http` loader for thumbor which provides additional statistics (like width, height and url parsing)
Home-page: https://github.com/BowlingX/thumbor-http-stats-loader
Author: David Heidrich
Author-email: me@bowlingx.com
License: MIT
License-File: LICENSE
Requires-Dist: thumbor (<8,>=7.0.0a2)
